git_truckfactor/__init__.py
git_truckfactor/developer_network.py
git_truckfactor/metrics.py
git_truckfactor/truckfactor.py
git_truckfactor/version.py
git_truckfactor-0.1.0.dist-info/LICENSE
git_truckfactor-0.1.0.dist-info/METADATA
git_truckfactor-0.1.0.dist-info/WHEEL
git_truckfactor-0.1.0.dist-info/top_level.txt
git_truckfactor-0.1.0.dist-info/RECORD
