Metadata-Version: 2.1
Name: git-truckfactor
Version: 0.1.0
Summary: Calculate code contribution metrics for git repositories
Home-page: https://github.com/PhilRett/gitmetrics
Author: Philipp Rettig
Author-email: ph.rettig13@gmail.com
License: UNKNOWN
Platform: UNKNOWN
Classifier: Development Status :: 4 - Beta
Classifier: Intended Audience :: Science/Research
Classifier: Programming Language :: Python :: 3.9
Requires-Dist: numpy
Requires-Dist: networkx
